hello_robot_stretch_tool_share-0.3.4.data/scripts/reactor_wrist_jog.py
stretch_tool_share/__init__.py
stretch_tool_share/dry_erase_holder_v1/__init__.py
stretch_tool_share/dry_erase_holder_v1/command_groups.py
stretch_tool_share/dry_erase_holder_v1/params.py
stretch_tool_share/dry_erase_holder_v1/tool.py
stretch_tool_share/reactorx_wrist_v1/__init__.py
stretch_tool_share/reactorx_wrist_v1/command_groups.py
stretch_tool_share/reactorx_wrist_v1/params.py
stretch_tool_share/reactorx_wrist_v1/reactor_gripper.py
stretch_tool_share/reactorx_wrist_v1/tool.py
stretch_tool_share/reactorx_wrist_v1/wrist_pitch.py
stretch_tool_share/reactorx_wrist_v1/wrist_roll.py
stretch_tool_share/usbcam_wrist_v1/__init__.py
stretch_tool_share/usbcam_wrist_v1/command_groups.py
stretch_tool_share/usbcam_wrist_v1/offset_wrist_yaw.py
stretch_tool_share/usbcam_wrist_v1/params.py
stretch_tool_share/usbcam_wrist_v1/tool.py
stretch_tool_share_se3/eoa_wrist_dw3_tool_tablet_12in/__init__.py
stretch_tool_share_se3/eoa_wrist_dw3_tool_tablet_12in/params.py
stretch_tool_share_se3/eoa_wrist_dw3_tool_tablet_12in/tool.py
hello_robot_stretch_tool_share-0.3.4.dist-info/LICENSE.md
hello_robot_stretch_tool_share-0.3.4.dist-info/METADATA
hello_robot_stretch_tool_share-0.3.4.dist-info/WHEEL
hello_robot_stretch_tool_share-0.3.4.dist-info/top_level.txt
hello_robot_stretch_tool_share-0.3.4.dist-info/RECORD
