Metadata-Version: 2.1
Name: hello-robot-stretch-tool-share
Version: 0.3.4
Summary: Stretch end of arm tool interfaces
Home-page: https://github.com/hello-robot/stretch_tool_share
Author: Hello Robot Inc.
Author-email: support@hello-robot.com
License: UNKNOWN
Platform: UNKNOWN
Classifier: Programming Language :: Python :: 2
Classifier: Operating System :: OS Independent
Classifier: License :: OSI Approved :: GNU Lesser General Public License v3 (LGPLv3)
License-File: LICENSE.md
